{
    "title": "FluxCD: Get Started",
    "description": "The FluxCD Getting started guide - in your browser",
    "details": {
      "intro": {
        "title": "Welcome to FluxCD",
        "text": "intro.md",
        "foreground": "assets/scripts/foreground.sh"
      },
      "steps": [
        {
            "title": "Install Flux",
            "text": "step1.md"
        }, {
            "title": "Install podinfo",
            "text": "step2.md"
        }, {
            "title": "Customise podinfo",
            "text": "step3.md"
        }, {
            "title": "Create Namespace",
            "text": "step4.md"
        }
      ],
      "finish": {
        "text": "finish.md"
      }
    },
    "backend": {
      "imageid": "kubernetes-kubeadm-1node"
    }
  }
  